MoNeT_MGDrivE/__init__.py
MoNeT_MGDrivE/_version.py
MoNeT_MGDrivE/aggregateSpatial.py
MoNeT_MGDrivE/auxiliaryFunctions.py
MoNeT_MGDrivE/colors.py
MoNeT_MGDrivE/dataAnalysis.py
MoNeT_MGDrivE/experimentsHandler.py
MoNeT_MGDrivE/experimentsHandlerAlt.py
MoNeT_MGDrivE/experimentsHandlerEpi.py
MoNeT_MGDrivE/factorialExperimentsHandler.py
MoNeT_MGDrivE/factorialSensitivity.py
MoNeT_MGDrivE/genes.py
MoNeT_MGDrivE/landscape.py
MoNeT_MGDrivE/mailAlert.py
MoNeT_MGDrivE/mlModels.py
MoNeT_MGDrivE/parallel.py
MoNeT_MGDrivE/plots.py
MoNeT_MGDrivE/plotsOverlays.py
MoNeT_MGDrivE/preprocess.py
MoNeT_MGDrivE/spatialVideos.py
MoNeT_MGDrivE/spatialVideosLegacy.py
MoNeT_MGDrivE/summaryStatistics.py
MoNeT_MGDrivE/terminal.py
MoNeT_MGDrivE/tracesHandler.py
MoNeT_MGDrivE-0.9.1.1.dist-info/LICENSE.txt
MoNeT_MGDrivE-0.9.1.1.dist-info/METADATA
MoNeT_MGDrivE-0.9.1.1.dist-info/WHEEL
MoNeT_MGDrivE-0.9.1.1.dist-info/top_level.txt
MoNeT_MGDrivE-0.9.1.1.dist-info/RECORD
