Metadata-Version: 2.1
Name: MoNeT-MGDrivE
Version: 0.9.1.1
Summary: MoNeT python package for MGDrivE data analysis
Home-page: https://github.com/Chipdelmal/MoNeT_MGDrivE
Author: Hector M. Sanchez C.
Author-email: sanchez.hmsc@berkeley.edu
License: MIT
Classifier: Programming Language :: Python :: 3.8
Classifier: Operating System :: OS Independent
License-File: LICENSE.txt
Requires-Dist: numpy
Requires-Dist: scipy
Requires-Dist: matplotlib
Requires-Dist: ipython
Requires-Dist: jupyter
Requires-Dist: pandas
Requires-Dist: sympy
Requires-Dist: compress-pickle
Requires-Dist: joblib
Requires-Dist: more-itertools
